metasheet/__init__.py
metasheet/classes.py
metasheet/config.json
metasheet/excel.py
metasheet/repository.py
metasheet/serializers/__init__.py
metasheet/serializers/aria.py
metasheet/serializers/aria_changes.py
metasheet/serializers/bq.py
metasheet/serializers/ddi.py
metasheet/serializers/mockaroo.py
metasheet/serializers/py.py
metasheet/serializers/rds.py
metasheet/serializers/rml.py
metasheet/serializers/sql.py
metasheet/serializers/sts.py
metasheet-0.2.2.data/scripts/metasheet
metasheet-0.2.2.dist-info/LICENSE
metasheet-0.2.2.dist-info/METADATA
metasheet-0.2.2.dist-info/WHEEL
metasheet-0.2.2.dist-info/top_level.txt
metasheet-0.2.2.dist-info/RECORD
