Metadata-Version: 2.1
Name: metasheet
Version: 0.2.2
Summary: Metasheet parser, serializers, and repository manager
Author: Pascal Heus
Author-email: pascal.heus@mtna.us
Project-URL: Maintainer, http://www.mtna.us
Classifier: Development Status :: 4 - Beta
Classifier: Intended Audience :: Science/Research
Classifier: Topic :: Scientific/Engineering
Classifier: License :: OSI Approved :: MIT License
Classifier: Programming Language :: Python :: 3
Requires-Python: >=3.6
License-File: LICENSE
Requires-Dist: openpyxl
Requires-Dist: python-dateutil
